circleci_to_sqlite/__init__.py
circleci_to_sqlite/cli.py
circleci_to_sqlite/utils.py
circleci_to_sqlite-0.3.1.dist-info/LICENSE
circleci_to_sqlite-0.3.1.dist-info/METADATA
circleci_to_sqlite-0.3.1.dist-info/WHEEL
circleci_to_sqlite-0.3.1.dist-info/entry_points.txt
circleci_to_sqlite-0.3.1.dist-info/top_level.txt
circleci_to_sqlite-0.3.1.dist-info/RECORD
