Metadata-Version: 2.1
Name: circleci-to-sqlite
Version: 0.3.1
Summary: Save data from CircleCI to a SQLite database
Home-page: https://github.com/seem/circleci-to-sqlite
Author: Wasim Lorgat
License: Apache License, Version 2.0
Platform: UNKNOWN
Requires-Dist: sqlite-utils (>=2.7.2)
Requires-Dist: requests
Provides-Extra: test
Requires-Dist: pytest ; extra == 'test'
Requires-Dist: requests-mock ; extra == 'test'
Requires-Dist: bs4 ; extra == 'test'
